amida/__init__.py
amida/py.typed
amida-0.0.1.dist-info/WHEEL
amida-0.0.1.dist-info/METADATA
amida-0.0.1.dist-info/RECORD
