Metadata-Version: 2.3
Name: amida
Version: 0.0.1
Summary: A comprehensive framework for building systems with high concurrency and low latency.
Author: zealeo
Author-email: zealeo <caozealeo@gmail.com>
Requires-Python: >=3.13
